<?xml version="1.0" ?>
<TEXT id="Wiki_Seediq_Fayez_al-Sarraj" xml:lang="trv" source="Seediq Wikipedia, article: Fayez_al-Sarraj" copyright="CC BY-SA" citation="Wikipedia contributors. (2026). Seediq Wikipedia. Wikimedia Foundation. Retrieved 2026-06-09, from https://trv.wikipedia.org/" BibTeX_citation="@misc{Wiki_trv, title = {Seediq Wikipedia}, author = {{Wikipedia contributors}}, year = {2026}, publisher = {Wikimedia Foundation}, url = {https://trv.wikipedia.org/}, urldate = {2026-06-09} }">
    <S id="0">
        <FORM kindOf="original">= Fayez al-Sarraj = Mntucing hngkawas 1960 idas jiyax ka Fayez al-Sarraj ga, empklaw ka hiya. Bukung klwaan Libya ta sayang o kiya ka Fayez al-Sarraj, pnaah hngkawas 2016 idas 3 jiyax 30 pnrajing kmlawa klwaan.</FORM>
        <PHON kindOf="original">= *ajə* al-saɾɾaɟ = mntuʦiŋ ħŋkawas **** idas ɟijax ka *ajə* al-saɾɾaɟ ga, əmpklaw ka ħija. bukuŋ klwaan libja ta sajaŋ o kija ka *ajə* al-saɾɾaɟ, pnaaħ ħŋkawas **** idas * ɟijax ** pnɾaɟiŋ kmlawa klwaan.</PHON>
        <FORM kindOf="standard">= Fayez al-Sarraj = Mntucing hngkawas 1960 idas jiyax ka Fayez al-Sarraj ga, empklaw ka hiya. Bukung klwaan Libya ta sayang o kiya ka Fayez al-Sarraj, pnaah hngkawas 2016 idas 3 jiyax 30 pnrajing kmlawa klwaan.</FORM>
        <PHON kindOf="standard">= *ajə* al-saɾɾaɟ = mntuʦiŋ ħŋkawas **** idas ɟijax ka *ajə* al-saɾɾaɟ ga, əmpklaw ka ħija. bukuŋ klwaan libja ta sajaŋ o kija ka *ajə* al-saɾɾaɟ, pnaaħ ħŋkawas **** idas * ɟijax ** pnɾaɟiŋ kmlawa klwaan.</PHON>
    </S>
</TEXT>