<?xml version="1.0" ?>
<TEXT id="Wiki_Seediq_Meuyas" xml:lang="trv" source="Seediq Wikipedia, article: Meuyas" copyright="CC BY-SA" citation="Wikipedia contributors. (2026). Seediq Wikipedia. Wikimedia Foundation. Retrieved 2026-06-09, from https://trv.wikipedia.org/" BibTeX_citation="@misc{Wiki_trv, title = {Seediq Wikipedia}, author = {{Wikipedia contributors}}, year = {2026}, publisher = {Wikimedia Foundation}, url = {https://trv.wikipedia.org/}, urldate = {2026-06-09} }">
    <S id="0">
        <FORM kindOf="original">= Meuyas = Dungus mu bi meuyas o, kika iyux psblaiq tnpusu sjiqan, tmbrih alang ksun.</FORM>
        <PHON kindOf="original">= məujas = duŋus mu bi məujas o, kika ijux psblaiq tnpusu sɟiqan, tmbɾiħ alaŋ ksun.</PHON>
        <FORM kindOf="standard">= Meuyas = Dungus mu bi meuyas o, kika iyux psblaiq tnpusu sjiqan, tmbrih alang ksun.</FORM>
        <PHON kindOf="standard">= məujas = duŋus mu bi məujas o, kika ijux psblaiq tnpusu sɟiqan, tmbɾiħ alaŋ ksun.</PHON>
    </S>
</TEXT>