<?xml version="1.0" ?>
<TEXT id="Wiki_Seediq_Saruc" xml:lang="trv" source="Seediq Wikipedia, article: Saruc" copyright="CC BY-SA" citation="Wikipedia contributors. (2026). Seediq Wikipedia. Wikimedia Foundation. Retrieved 2026-06-09, from https://trv.wikipedia.org/" BibTeX_citation="@misc{Wiki_trv, title = {Seediq Wikipedia}, author = {{Wikipedia contributors}}, year = {2026}, publisher = {Wikimedia Foundation}, url = {https://trv.wikipedia.org/}, urldate = {2026-06-09} }">
    <S id="0">
        <FORM kindOf="original">= Saruc = Gaga mniq Tawyuensu Fusingcyu ka alang Saruc. 44 sapah ka kneegu na sapah, 154 hiyi ka kana knhbragan na hiyi. Tnpusu seejiq o mangal 98% niqan 151 hiyi sp, rahuq na uxay tnpusu seejiq o mangal 2% niqan 3 hiyi koia. Kana ka kleegan seejiq ga, Tayal 95%, Amis 1%, Bunun 1%, ni rahuq na o 1%. Pnyahan pnatas</FORM>
        <PHON kindOf="original">= saɾuʦ = gaga mniq tawjuənsu *usiŋʦju ka alaŋ saɾuʦ. ** sapaħ ka knəəgu na sapaħ, *** ħiji ka kana knħbɾagan na ħiji. tnpusu səəɟiq o maŋal **% niqan *** ħiji sp, ɾaħuq na uxaj tnpusu səəɟiq o maŋal *% niqan * ħiji koia. kana ka kləəgan səəɟiq ga, tajal **%, amis *%, bunun *%, ni ɾaħuq na o *%. pnjaħan pnatas</PHON>
        <FORM kindOf="standard">= Saruc = Gaga mniq Tawyuensu Fusingcyu ka alang Saruc. 44 sapah ka kneegu na sapah, 154 hiyi ka kana knhbragan na hiyi. Tnpusu seejiq o mangal 98% niqan 151 hiyi sp, rahuq na uxay tnpusu seejiq o mangal 2% niqan 3 hiyi koia. Kana ka kleegan seejiq ga, Tayal 95%, Amis 1%, Bunun 1%, ni rahuq na o 1%. Pnyahan pnatas</FORM>
        <PHON kindOf="standard">= saɾuʦ = gaga mniq tawjuənsu *usiŋʦju ka alaŋ saɾuʦ. ** sapaħ ka knəəgu na sapaħ, *** ħiji ka kana knħbɾagan na ħiji. tnpusu səəɟiq o maŋal **% niqan *** ħiji sp, ɾaħuq na uxaj tnpusu səəɟiq o maŋal *% niqan * ħiji koia. kana ka kləəgan səəɟiq ga, tajal **%, amis *%, bunun *%, ni ɾaħuq na o *%. pnjaħan pnatas</PHON>
    </S>
</TEXT>