<?xml version="1.0" ?>
<TEXT id="Wiki_Seediq_Tslusuq" xml:lang="trv" source="Seediq Wikipedia, article: Tslusuq" copyright="CC BY-SA" citation="Wikipedia contributors. (2026). Seediq Wikipedia. Wikimedia Foundation. Retrieved 2026-06-09, from https://trv.wikipedia.org/" BibTeX_citation="@misc{Wiki_trv, title = {Seediq Wikipedia}, author = {{Wikipedia contributors}}, year = {2026}, publisher = {Wikimedia Foundation}, url = {https://trv.wikipedia.org/}, urldate = {2026-06-09} }">
    <S id="0">
        <FORM kindOf="original">= Tslusuq = Ex:Wada sonii ka ndaan laqi mqedin sluhe tminun cbeyo, asika tslusuq ma tmmeling betaq mkela. Pnyahan pnatas</FORM>
        <PHON kindOf="original">= tslusuq = əx:wada sonii ka ndaan laqi mqədin sluħə tminun ʦbəo, asika tslusuq ma tmməliŋ bətaq mkəla. pnjaħan pnatas</PHON>
        <FORM kindOf="standard">= Tslusuq = Ex:Wada sonii ka ndaan laqi mqedin sluhe tminun cbeyo, asika tslusuq ma tmmeling betaq mkela. Pnyahan pnatas</FORM>
        <PHON kindOf="standard">= tslusuq = əx:wada sonii ka ndaan laqi mqədin sluħə tminun ʦbəo, asika tslusuq ma tmməliŋ bətaq mkəla. pnjaħan pnatas</PHON>
    </S>
</TEXT>