<?xml version="1.0" ?>
<TEXT id="Wiki_Amis_Qapuciu" xml:lang="ami" source="Amis Wikipedia, article: Qapuciu" copyright="CC BY-SA" citation="Qapuciu. (2025, May 05). In Wikipedia [Amis]. https://ami.wikipedia.org/wiki/Qapuciu" BibTeX_citation="@misc{Wiki_ami_Qapuciu, title = Qapuciu, year = 2025, month = May, day = 5, note = {In Wikipedia [Amis]}, url = {https://ami.wikipedia.org/wiki/Qapuciu} }">
    <S id="0">
        <FORM kindOf="original">Qapuciu Itiniay i Xinyi Cen no Nantou ko Qapuciu a niyaro', 105 ko sa'osi no parod no loma', 321 ko sa'osi no tamdaw. 55% ko ka'aloman no Yincomin, polong han i, 175 ko tamdaw; o roma sato i, 45% ko ka'aloman no roma a finacadan, polong han i, 146 ko tamdaw. O pa-sin-to no ka'aloman no tamdaw no kasafinacadan i, ko Bunun54%, Tayal1%.</FORM>
        <PHON kindOf="original">*apo~u~u ¶io~u~u itiniaj i xinji  ¶…ôn no~u nanto~uo~u~u ko~u *apo~u~u ¶io~u~u a nijaro~u °, *** ko~u sa °o~usi no~u paro~u…¨~…ģ no~u …ĺo~uma °, *** ko~u sa °o~usi no~u tam…¨~…ģaw. **% ko~u ka °a…ĺo~uman no~u jin ¶o~umin, po~u…ĺo~uŇč ńßan i, *** ko~u tam…¨~…ģaw; o~u ro~uma sato~u i, **% ko~u ka °a…ĺo~uman no~u ro~uma a fina ¶a…¨~…ģan, po~u…ĺo~uŇč ńßan i, *** ko~u tam…¨~…ģaw. o~u pa-sin-to~u no~u ka °a…ĺo~uman no~u tam…¨~…ģaw no~u kasafina ¶a…¨~…ģan i, ko~u b~b~vo~u~uno~u~un**%, taja…ĺ*%.</PHON>
        <FORM kindOf="standard">Qapuciu Itiniay i Xinyi Cen no Nantou ko Qapuciu a niyaro', 105 ko sa'osi no parod no loma', 321 ko sa'osi no tamdaw. 55% ko ka'aloman no Yincomin, polong han i, 175 ko tamdaw; o roma sato i, 45% ko ka'aloman no roma a finacadan, polong han i, 146 ko tamdaw. O pa-sin-to no ka'aloman no tamdaw no kasafinacadan i, ko Bunun54%, Tayal1%.</FORM>
        <PHON kindOf="standard">*apo~u~u ¶io~u~u itiniaj i xinji  ¶…ôn no~u nanto~uo~u~u ko~u *apo~u~u ¶io~u~u a nijaro~u °, *** ko~u sa °o~usi no~u paro~u…¨~…ģ no~u …ĺo~uma °, *** ko~u sa °o~usi no~u tam…¨~…ģaw. **% ko~u ka °a…ĺo~uman no~u jin ¶o~umin, po~u…ĺo~uŇč ńßan i, *** ko~u tam…¨~…ģaw; o~u ro~uma sato~u i, **% ko~u ka °a…ĺo~uman no~u ro~uma a fina ¶a…¨~…ģan, po~u…ĺo~uŇč ńßan i, *** ko~u tam…¨~…ģaw. o~u pa-sin-to~u no~u ka °a…ĺo~uman no~u tam…¨~…ģaw no~u kasafina ¶a…¨~…ģan i, ko~u b~b~vo~u~uno~u~un**%, taja…ĺ*%.</PHON>
    </S>
</TEXT>