<?xml version="1.0" ?>
<TEXT id="Wiki_Amis_Siri" xml:lang="ami" source="Amis Wikipedia, article: Siri" copyright="CC BY-SA" citation="Wikipedia contributors. (2026). Amis Wikipedia. Wikimedia Foundation. Retrieved 2026-06-09, from https://ami.wikipedia.org/" BibTeX_citation="@misc{Wiki_ami, title = {Amis Wikipedia}, author = {{Wikipedia contributors}}, year = {2026}, publisher = {Wikimedia Foundation}, url = {https://ami.wikipedia.org/}, urldate = {2026-06-09} }">
    <S id="0">
        <FORM kindOf="original">Ono 哺乳類 a pina'orip konini. Iraay ko 蹄(sackih) ato wa'a. Ira ko tosaay a siri i Taywan i 'ayaw, o 褐色山羊 ato 台灣長鬃山羊. O ccay ngafol ko 台灣長鬃山羊. Kakako pasiiked 域(sofol):ma'oripay 界(salawacan):aadopen 門(fawahan):sakololay 綱(opir):pacocoay 目 (mata):tosa-sackih 科 :kolong 屬 :siri O serangawan I serangawan no Holam i, tadafangcalay a 'a'adopen ko siri. I serangawan no ka'etipay a kanatal i, o cicediay ko pinangan no siri, o homikayay ko pinangan no tadasiri. I Yotaya a kanatal i, o maliyangay ko siri, o mitengilay ko tadasiri.</FORM>
        <PHON kindOf="original">o~uno~u *** a pinaʡo~urip ko~unini. iraaj ko~u *(saʦkiħ) ato~u waʡa. ira ko~u to~usaaj a siri i tajwan i ʡajaw, o~u **** ato~u ******. o~u ʦʦaj ŋafo~uɾ ko~u ******. kakako~u pasiikəɬ~ɮ *(so~ufo~uɾ):maʡo~uripaj *(saɾawaʦan):aaɬ~ɮo~upən *(fawaħan):sako~uɾo~uɾaj *(o~upir):paʦo~uʦo~uaj * (mata):to~usa-saʦkiħ * :ko~uɾo~uŋ * :siri o~u səraŋawan i səraŋawan no~u ħo~uɾam i, taɬ~ɮafaŋʦaɾaj a ʡaʡaɬ~ɮo~upən ko~u siri. i səraŋawan no~u kaʡətipaj a kanataɾ i, o~u ʦiʦəɬ~ɮiaj ko~u pinaŋan no~u siri, o~u ħo~umikajaj ko~u pinaŋan no~u taɬ~ɮasiri. i jo~utaja a kanataɾ i, o~u maɾijaŋaj ko~u siri, o~u mitəŋiɾaj ko~u taɬ~ɮasiri.</PHON>
        <FORM kindOf="standard">Ono 哺乳類 a pina'orip konini. Iraay ko 蹄(sackih) ato wa'a. Ira ko tosaay a siri i Taywan i 'ayaw, o 褐色山羊 ato 台灣長鬃山羊. O ccay ngafol ko 台灣長鬃山羊. Kakako pasiiked 域(sofol):ma'oripay 界(salawacan):aadopen 門(fawahan):sakololay 綱(opir):pacocoay 目 (mata):tosa-sackih 科 :kolong 屬 :siri O serangawan I serangawan no Holam i, tadafangcalay a 'a'adopen ko siri. I serangawan no ka'etipay a kanatal i, o cicediay ko pinangan no siri, o homikayay ko pinangan no tadasiri. I Yotaya a kanatal i, o maliyangay ko siri, o mitengilay ko tadasiri.</FORM>
        <PHON kindOf="standard">o~uno~u *** a pinaʡo~urip ko~unini. iraaj ko~u *(saʦkiħ) ato~u waʡa. ira ko~u to~usaaj a siri i tajwan i ʡajaw, o~u **** ato~u ******. o~u ʦʦaj ŋafo~uɾ ko~u ******. kakako~u pasiikəɬ~ɮ *(so~ufo~uɾ):maʡo~uripaj *(saɾawaʦan):aaɬ~ɮo~upən *(fawaħan):sako~uɾo~uɾaj *(o~upir):paʦo~uʦo~uaj * (mata):to~usa-saʦkiħ * :ko~uɾo~uŋ * :siri o~u səraŋawan i səraŋawan no~u ħo~uɾam i, taɬ~ɮafaŋʦaɾaj a ʡaʡaɬ~ɮo~upən ko~u siri. i səraŋawan no~u kaʡətipaj a kanataɾ i, o~u ʦiʦəɬ~ɮiaj ko~u pinaŋan no~u siri, o~u ħo~umikajaj ko~u pinaŋan no~u taɬ~ɮasiri. i jo~utaja a kanataɾ i, o~u maɾijaŋaj ko~u siri, o~u mitəŋiɾaj ko~u taɬ~ɮasiri.</PHON>
    </S>
</TEXT>