<?xml version="1.0" ?>
<TEXT id="NTU_Stry_Seediq_sdqNr-tattoo2_pawan 2020s" xml:lang="trv" source="NTU Corpus stories for Seediq, story: sdqNr-tattoo2_pawan 2020s" audio="diarized" copyright="" citation="" BibTeX_citation="">
    <S id="S_0">
        <FORM>a mqedin mesa rudan cbeyo wa asi ka jyunansay sa patisan sa.</FORM>
        <TRANSL xml:lang="zh"> 據說，我們的女性祖先必須到了十幾歲的時候才可以紋面。</TRANSL>
        <TRANSL xml:lang="en"> It is said that our ancestors cannot get their faces tattooed until their are at least teenage.</TRANSL>
        <W id="S0W0">
            <FORM>a==</FORM>
            <M id="S0W0M0_0">
                <FORM>a==</FORM>
                <TRANSL>FIL</TRANSL>
                <TRANSL ver="zh_gloss">FIL</TRANSL>
            </M>
        </W>
        <W id="S0W1">
            <FORM>mqedin</FORM>
            <M id="S0W1M0_0">
                <FORM>mqedin</FORM>
                <TRANSL>woman</TRANSL>
                <TRANSL ver="zh_gloss">女人</TRANSL>
            </M>
        </W>
        <W id="S0W2">
            <FORM>mesa</FORM>
            <M id="S0W2M0_0">
                <FORM>mesa</FORM>
                <TRANSL>AF.say</TRANSL>
                <TRANSL ver="zh_gloss">主焦.說</TRANSL>
            </M>
        </W>
        <W id="S0W3">
            <FORM>rudan</FORM>
            <M id="S0W3M0_0">
                <FORM>rudan</FORM>
                <TRANSL>elderly</TRANSL>
                <TRANSL ver="zh_gloss">長者</TRANSL>
            </M>
        </W>
        <W id="S0W4">
            <FORM>cbeyo</FORM>
            <M id="S0W4M0_0">
                <FORM>cbeyo</FORM>
                <TRANSL>past</TRANSL>
                <TRANSL ver="zh_gloss">以前</TRANSL>
            </M>
        </W>
        <W id="S0W5">
            <FORM>wa</FORM>
            <M id="S0W5M0_0">
                <FORM>wa</FORM>
                <TRANSL>FIL</TRANSL>
                <TRANSL ver="zh_gloss">FIL</TRANSL>
            </M>
        </W>
        <W id="S0W6">
            <FORM>asi</FORM>
            <M id="S0W6M0_0">
                <FORM>asi</FORM>
                <TRANSL>must</TRANSL>
                <TRANSL ver="zh_gloss">一定</TRANSL>
            </M>
        </W>
        <W id="S0W7">
            <FORM>ka</FORM>
            <M id="S0W7M0_0">
                <FORM>ka</FORM>
                <TRANSL>KA</TRANSL>
                <TRANSL ver="zh_gloss">KA</TRANSL>
            </M>
        </W>
        <W id="S0W8">
            <FORM>&lt;L2JjyunansayL2J&gt;</FORM>
            <M id="S0W8M0_0">
                <FORM>&lt;L2JjyunansayL2J&gt;</FORM>
                <TRANSL>&lt;L2JteenageL2J&gt;</TRANSL>
                <TRANSL ver="zh_gloss">&lt;L2J十幾歲L2J&gt;</TRANSL>
            </M>
        </W>
        <W id="S0W9">
            <FORM>sa</FORM>
            <M id="S0W9M0_0">
                <FORM>sa</FORM>
                <TRANSL>say</TRANSL>
                <TRANSL ver="zh_gloss">說</TRANSL>
            </M>
        </W>
        <W id="S0W10">
            <FORM>patis-an</FORM>
            <M id="S0W10M0_0">
                <FORM>patis</FORM>
                <TRANSL>face.tattoo</TRANSL>
                <TRANSL ver="zh_gloss">紋面</TRANSL>
            </M>
            <M id="S0W10M1_0">
                <FORM>an</FORM>
                <TRANSL>LF</TRANSL>
                <TRANSL ver="zh_gloss">處焦</TRANSL>
            </M>
        </W>
        <W id="S0W11">
            <FORM>sa</FORM>
            <M id="S0W11M0_0">
                <FORM>sa</FORM>
                <TRANSL>say</TRANSL>
                <TRANSL ver="zh_gloss">說</TRANSL>
            </M>
        </W>
    </S>
    <S id="S_1">
        <FORM>patisun daha a a dqeras malux patisan so.</FORM>
        <TRANSL xml:lang="zh"> 為什麼要紋面呢？</TRANSL>
        <TRANSL xml:lang="en"> Why do they tattoo their faces?</TRANSL>
        <W id="S1W0">
            <FORM>patis-un=daha</FORM>
            <M id="S1W0M0_0">
                <FORM>patis</FORM>
                <TRANSL>face.tattoo</TRANSL>
                <TRANSL ver="zh_gloss">紋面</TRANSL>
            </M>
            <M id="S1W0M1_0">
                <FORM>un</FORM>
                <TRANSL>PF</TRANSL>
                <TRANSL ver="zh_gloss">受焦</TRANSL>
            </M>
            <M id="S1W0M1_1">
                <FORM>daha</FORM>
                <TRANSL>3PL.GEN</TRANSL>
                <TRANSL ver="zh_gloss">3PL.屬格</TRANSL>
            </M>
        </W>
        <W id="S1W1">
            <FORM>a==</FORM>
            <M id="S1W1M0_0">
                <FORM>a==</FORM>
                <TRANSL>FIL</TRANSL>
                <TRANSL ver="zh_gloss">FIL</TRANSL>
            </M>
        </W>
        <W id="S1W2">
            <FORM>a==</FORM>
            <M id="S1W2M0_0">
                <FORM>a==</FORM>
                <TRANSL>FIL</TRANSL>
                <TRANSL ver="zh_gloss">FIL</TRANSL>
            </M>
        </W>
        <W id="S1W3">
            <FORM>dqeras</FORM>
            <M id="S1W3M0_0">
                <FORM>dqeras</FORM>
                <TRANSL>face</TRANSL>
                <TRANSL ver="zh_gloss">臉</TRANSL>
            </M>
        </W>
        <W id="S1W4">
            <FORM>m-alux</FORM>
            <M id="S1W4M0_0">
                <FORM>m</FORM>
                <TRANSL>AF</TRANSL>
                <TRANSL ver="zh_gloss">主焦</TRANSL>
            </M>
            <M id="S1W4M1_0">
                <FORM>alux</FORM>
                <TRANSL>why</TRANSL>
                <TRANSL ver="zh_gloss">為什麼</TRANSL>
            </M>
        </W>
        <W id="S1W5">
            <FORM>patis-an</FORM>
            <M id="S1W5M0_0">
                <FORM>patis</FORM>
                <TRANSL>face.tattoo</TRANSL>
                <TRANSL ver="zh_gloss">紋面</TRANSL>
            </M>
            <M id="S1W5M1_0">
                <FORM>an</FORM>
                <TRANSL>LF</TRANSL>
                <TRANSL ver="zh_gloss">處焦</TRANSL>
            </M>
        </W>
        <W id="S1W6">
            <FORM>so/</FORM>
            <M id="S1W6M0_0">
                <FORM>so/</FORM>
                <TRANSL>be.like</TRANSL>
                <TRANSL ver="zh_gloss">像這樣</TRANSL>
            </M>
        </W>
    </S>
    <S id="S_2">
        <FORM>malu qitaan.</FORM>
        <TRANSL xml:lang="zh"> [因為] 漂亮。</TRANSL>
        <TRANSL xml:lang="en"> [because it makes them] beautiful.</TRANSL>
        <W id="S2W0">
            <FORM>malu</FORM>
            <M id="S2W0M0_0">
                <FORM>malu</FORM>
                <TRANSL>AF.good</TRANSL>
                <TRANSL ver="zh_gloss">主焦.好</TRANSL>
            </M>
        </W>
        <W id="S2W1">
            <FORM>qita-an</FORM>
            <M id="S2W1M0_0">
                <FORM>qita</FORM>
                <TRANSL>see</TRANSL>
                <TRANSL ver="zh_gloss">看</TRANSL>
            </M>
            <M id="S2W1M1_0">
                <FORM>an</FORM>
                <TRANSL>LF</TRANSL>
                <TRANSL ver="zh_gloss">處焦</TRANSL>
            </M>
        </W>
    </S>
    <S id="S_3">
        <FORM>ini kkerung si ma.</FORM>
        <TRANSL xml:lang="zh"> [臉] 不會起皺紋。</TRANSL>
        <TRANSL xml:lang="en"> [their faces] would not wrinkle.</TRANSL>
        <W id="S3W0">
            <FORM>ini</FORM>
            <M id="S3W0M0_0">
                <FORM>ini</FORM>
                <TRANSL>NEG</TRANSL>
                <TRANSL ver="zh_gloss">否定</TRANSL>
            </M>
        </W>
        <W id="S3W1">
            <FORM>kkerung</FORM>
            <M id="S3W1M0_0">
                <FORM>kkerung</FORM>
                <TRANSL>wrinkle.up</TRANSL>
                <TRANSL ver="zh_gloss">起皺紋</TRANSL>
            </M>
        </W>
        <W id="S3W2">
            <FORM>si</FORM>
            <M id="S3W2M0_0">
                <FORM>si</FORM>
                <TRANSL>say</TRANSL>
                <TRANSL ver="zh_gloss">說</TRANSL>
            </M>
        </W>
        <W id="S3W3">
            <FORM>ma</FORM>
            <M id="S3W3M0_0">
                <FORM>ma</FORM>
                <TRANSL>then</TRANSL>
                <TRANSL ver="zh_gloss">然後</TRANSL>
            </M>
        </W>
    </S>
    <S id="S_4">
        <FORM>a mtbeno klaali qitaan dqeras daha si.</FORM>
        <TRANSL xml:lang="zh"> 據說紋面後，他們每天臉看起來都是豐腴的。</TRANSL>
        <TRANSL xml:lang="en"> It is said that after getting their faces tatooed their faces look plump every day.</TRANSL>
        <W id="S4W0">
            <FORM>a==</FORM>
            <M id="S4W0M0_0">
                <FORM>a==</FORM>
                <TRANSL>FIL</TRANSL>
                <TRANSL ver="zh_gloss">FIL</TRANSL>
            </M>
        </W>
        <W id="S4W1">
            <FORM>m-tbeno</FORM>
            <M id="S4W1M0_0">
                <FORM>m</FORM>
                <TRANSL>AF</TRANSL>
                <TRANSL ver="zh_gloss">主焦</TRANSL>
            </M>
            <M id="S4W1M1_0">
                <FORM>tbeno</FORM>
                <TRANSL>plump</TRANSL>
                <TRANSL ver="zh_gloss">豐腴</TRANSL>
            </M>
        </W>
        <W id="S4W2">
            <FORM>klaali</FORM>
            <M id="S4W2M0_0">
                <FORM>klaali</FORM>
                <TRANSL>every.day</TRANSL>
                <TRANSL ver="zh_gloss">每天</TRANSL>
            </M>
        </W>
        <W id="S4W3">
            <FORM>qita-an</FORM>
            <M id="S4W3M0_0">
                <FORM>qita</FORM>
                <TRANSL>see</TRANSL>
                <TRANSL ver="zh_gloss">看</TRANSL>
            </M>
            <M id="S4W3M1_0">
                <FORM>an</FORM>
                <TRANSL>LF</TRANSL>
                <TRANSL ver="zh_gloss">處焦</TRANSL>
            </M>
        </W>
        <W id="S4W4">
            <FORM>dqeras=daha</FORM>
            <M id="S4W4M0_0">
                <FORM>dqeras</FORM>
                <TRANSL>face</TRANSL>
                <TRANSL ver="zh_gloss">臉</TRANSL>
            </M>
            <M id="S4W4M0_1">
                <FORM>daha</FORM>
                <TRANSL>3PL.GEN</TRANSL>
                <TRANSL ver="zh_gloss">3PL.屬格</TRANSL>
            </M>
        </W>
        <W id="S4W5">
            <FORM>si</FORM>
            <M id="S4W5M0_0">
                <FORM>si</FORM>
                <TRANSL>say</TRANSL>
                <TRANSL ver="zh_gloss">說</TRANSL>
            </M>
        </W>
    </S>
    <S id="S_5">
        <FORM>ma meniq a.</FORM>
        <TRANSL xml:lang="zh"> 另外呢，</TRANSL>
        <TRANSL xml:lang="en"> besides,</TRANSL>
        <W id="S5W0">
            <FORM>ma==</FORM>
            <M id="S5W0M0_0">
                <FORM>ma==</FORM>
                <TRANSL>then</TRANSL>
                <TRANSL ver="zh_gloss">然後</TRANSL>
            </M>
        </W>
        <W id="S5W1">
            <FORM>m-eniq</FORM>
            <M id="S5W1M0_0">
                <FORM>m</FORM>
                <TRANSL>AF</TRANSL>
                <TRANSL ver="zh_gloss">主焦</TRANSL>
            </M>
            <M id="S5W1M1_0">
                <FORM>eniq</FORM>
                <TRANSL>be.at</TRANSL>
                <TRANSL ver="zh_gloss">在</TRANSL>
            </M>
        </W>
        <W id="S5W2">
            <FORM>a==</FORM>
            <M id="S5W2M0_0">
                <FORM>a==</FORM>
                <TRANSL>FIL</TRANSL>
                <TRANSL ver="zh_gloss">FIL</TRANSL>
            </M>
        </W>
    </S>
    <S id="S_6">
        <FORM>sricuh daha si o.</FORM>
        <TRANSL xml:lang="zh"> 她們用什麼東西擦咧？</TRANSL>
        <TRANSL xml:lang="en"> What do they use to powder their faces?</TRANSL>
        <W id="S6W0">
            <FORM>s-ricuh=daha</FORM>
            <M id="S6W0M0_0">
                <FORM>s</FORM>
                <TRANSL>RF</TRANSL>
                <TRANSL ver="zh_gloss">參焦</TRANSL>
            </M>
            <M id="S6W0M1_0">
                <FORM>ricuh</FORM>
                <TRANSL>powder</TRANSL>
                <TRANSL ver="zh_gloss">擦</TRANSL>
            </M>
            <M id="S6W0M1_1">
                <FORM>daha</FORM>
                <TRANSL>3PL.NOM</TRANSL>
                <TRANSL ver="zh_gloss">3PL.主格</TRANSL>
            </M>
        </W>
        <W id="S6W1">
            <FORM>si</FORM>
            <M id="S6W1M0_0">
                <FORM>si</FORM>
                <TRANSL>say</TRANSL>
                <TRANSL ver="zh_gloss">說</TRANSL>
            </M>
        </W>
        <W id="S6W2">
            <FORM>o</FORM>
            <M id="S6W2M0_0">
                <FORM>o</FORM>
                <TRANSL>FIL</TRANSL>
                <TRANSL ver="zh_gloss">FIL</TRANSL>
            </M>
        </W>
    </S>
    <S id="S_7">
        <FORM>dqeras ka ga n bagah henu so.</FORM>
        <TRANSL xml:lang="zh"> 臉...那個木炭...</TRANSL>
        <TRANSL xml:lang="en"> Face...that charcoal...</TRANSL>
        <W id="S7W0">
            <FORM>dqeras</FORM>
            <M id="S7W0M0_0">
                <FORM>dqeras</FORM>
                <TRANSL>face</TRANSL>
                <TRANSL ver="zh_gloss">臉</TRANSL>
            </M>
        </W>
        <W id="S7W1">
            <FORM>ka</FORM>
            <M id="S7W1M0_0">
                <FORM>ka</FORM>
                <TRANSL>NOM</TRANSL>
                <TRANSL ver="zh_gloss">主焦</TRANSL>
            </M>
        </W>
        <W id="S7W2">
            <FORM>ga</FORM>
            <M id="S7W2M0_0">
                <FORM>ga</FORM>
                <TRANSL>FS</TRANSL>
                <TRANSL ver="zh_gloss">FS</TRANSL>
            </M>
        </W>
        <W id="S7W3">
            <FORM>n</FORM>
            <M id="S7W3M0_0">
                <FORM>n</FORM>
                <TRANSL>FS</TRANSL>
                <TRANSL ver="zh_gloss">FS</TRANSL>
            </M>
        </W>
        <W id="S7W4">
            <FORM>bagah</FORM>
            <M id="S7W4M0_0">
                <FORM>bagah</FORM>
                <TRANSL>charcoal</TRANSL>
                <TRANSL ver="zh_gloss">木炭</TRANSL>
            </M>
        </W>
        <W id="S7W5">
            <FORM>henu</FORM>
            <M id="S7W5M0_0">
                <FORM>henu</FORM>
                <TRANSL>PART</TRANSL>
                <TRANSL ver="zh_gloss">語助詞</TRANSL>
            </M>
        </W>
        <W id="S7W6">
            <FORM>so</FORM>
            <M id="S7W6M0_0">
                <FORM>so</FORM>
                <TRANSL>be.like.this</TRANSL>
                <TRANSL ver="zh_gloss">像這樣</TRANSL>
            </M>
        </W>
    </S>
    <S id="S_8">
        <FORM>rkeruk harung si.</FORM>
        <TRANSL xml:lang="zh"> 據說就是那個二葉松的煙垢，</TRANSL>
        <TRANSL xml:lang="en"> It is said that is ashes of burned charcoal of pine.</TRANSL>
        <W id="S8W0">
            <FORM>rkeruk</FORM>
            <M id="S8W0M0_0">
                <FORM>rkeruk</FORM>
                <TRANSL>ashes.of.burned.charcoal</TRANSL>
                <TRANSL ver="zh_gloss">煙垢</TRANSL>
            </M>
        </W>
        <W id="S8W1">
            <FORM>harung</FORM>
            <M id="S8W1M0_0">
                <FORM>harung</FORM>
                <TRANSL>pine</TRANSL>
                <TRANSL ver="zh_gloss">二葉松</TRANSL>
            </M>
        </W>
        <W id="S8W2">
            <FORM>si</FORM>
            <M id="S8W2M0_0">
                <FORM>si</FORM>
                <TRANSL>say</TRANSL>
                <TRANSL ver="zh_gloss">說</TRANSL>
            </M>
        </W>
    </S>
    <S id="S_9">
        <FORM>a sricuh dqeras.</FORM>
        <TRANSL xml:lang="zh"> （拿來）擦臉。</TRANSL>
        <TRANSL xml:lang="en"> (which is used to) power the face</TRANSL>
        <W id="S9W0">
            <FORM>a</FORM>
            <M id="S9W0M0_0">
                <FORM>a</FORM>
                <TRANSL>FIL</TRANSL>
                <TRANSL ver="zh_gloss">FIL</TRANSL>
            </M>
        </W>
        <W id="S9W1">
            <FORM>s-ricuh</FORM>
            <M id="S9W1M0_0">
                <FORM>s</FORM>
                <TRANSL>RF</TRANSL>
                <TRANSL ver="zh_gloss">參焦</TRANSL>
            </M>
            <M id="S9W1M1_0">
                <FORM>ricuh</FORM>
                <TRANSL>powder</TRANSL>
                <TRANSL ver="zh_gloss">擦</TRANSL>
            </M>
        </W>
        <W id="S9W2">
            <FORM>dqeras</FORM>
            <M id="S9W2M0_0">
                <FORM>dqeras</FORM>
                <TRANSL>face</TRANSL>
                <TRANSL ver="zh_gloss">臉</TRANSL>
            </M>
        </W>
    </S>
    <S id="S_10">
        <FORM>kiya mqrehaq kii de so truma si ma.</FORM>
        <TRANSL xml:lang="zh"> （紋面的時候）煙垢最好是能滲透到臉皮裡面。</TRANSL>
        <TRANSL xml:lang="en"> (As for tattooing their face,) ashes of burned charcoal should go into their faces.</TRANSL>
        <W id="S10W0">
            <FORM>kiya==</FORM>
            <M id="S10W0M0_0">
                <FORM>kiya==</FORM>
                <TRANSL>that</TRANSL>
                <TRANSL ver="zh_gloss">那個</TRANSL>
            </M>
        </W>
        <W id="S10W1">
            <FORM>m-qrehaq</FORM>
            <M id="S10W1M0_0">
                <FORM>m</FORM>
                <TRANSL>AF</TRANSL>
                <TRANSL ver="zh_gloss">主焦</TRANSL>
            </M>
            <M id="S10W1M1_0">
                <FORM>qrehaq</FORM>
                <TRANSL>permeate</TRANSL>
                <TRANSL ver="zh_gloss">滲透</TRANSL>
            </M>
        </W>
        <W id="S10W2">
            <FORM>kii</FORM>
            <M id="S10W2M0_0">
                <FORM>kii</FORM>
                <TRANSL>that</TRANSL>
                <TRANSL ver="zh_gloss">那個</TRANSL>
            </M>
        </W>
        <W id="S10W3">
            <FORM>de</FORM>
            <M id="S10W3M0_0">
                <FORM>de</FORM>
                <TRANSL>PART</TRANSL>
                <TRANSL ver="zh_gloss">語助詞</TRANSL>
            </M>
        </W>
        <W id="S10W4">
            <FORM>so</FORM>
            <M id="S10W4M0_0">
                <FORM>so</FORM>
                <TRANSL>be.like.this</TRANSL>
                <TRANSL ver="zh_gloss">像這樣</TRANSL>
            </M>
        </W>
        <W id="S10W5">
            <FORM>truma</FORM>
            <M id="S10W5M0_0">
                <FORM>truma</FORM>
                <TRANSL>AF.deep</TRANSL>
                <TRANSL ver="zh_gloss">主焦.深</TRANSL>
            </M>
        </W>
        <W id="S10W6">
            <FORM>si</FORM>
            <M id="S10W6M0_0">
                <FORM>si</FORM>
                <TRANSL>say</TRANSL>
                <TRANSL ver="zh_gloss">說</TRANSL>
            </M>
        </W>
        <W id="S10W7">
            <FORM>ma</FORM>
            <M id="S10W7M0_0">
                <FORM>ma</FORM>
                <TRANSL>then</TRANSL>
                <TRANSL ver="zh_gloss">然後</TRANSL>
            </M>
        </W>
    </S>
    <S id="S_11">
        <FORM>mqrehaq si kii malu si.</FORM>
        <TRANSL xml:lang="zh"> 結痂、脫落之後，會比較好。</TRANSL>
        <TRANSL xml:lang="en"> After the scab falls off, [it would look] good.</TRANSL>
        <W id="S11W0">
            <FORM>m-qrehaq</FORM>
            <M id="S11W0M0_0">
                <FORM>m</FORM>
                <TRANSL>AF</TRANSL>
                <TRANSL ver="zh_gloss">主焦</TRANSL>
            </M>
            <M id="S11W0M1_0">
                <FORM>qrehaq</FORM>
                <TRANSL>crust.fall.off</TRANSL>
                <TRANSL ver="zh_gloss">痂脫落</TRANSL>
            </M>
        </W>
        <W id="S11W1">
            <FORM>si</FORM>
            <M id="S11W1M0_0">
                <FORM>si</FORM>
                <TRANSL>say</TRANSL>
                <TRANSL ver="zh_gloss">說</TRANSL>
            </M>
        </W>
        <W id="S11W2">
            <FORM>kii</FORM>
            <M id="S11W2M0_0">
                <FORM>kii</FORM>
                <TRANSL>this</TRANSL>
                <TRANSL ver="zh_gloss">這個</TRANSL>
            </M>
        </W>
        <W id="S11W3">
            <FORM>malu</FORM>
            <M id="S11W3M0_0">
                <FORM>malu</FORM>
                <TRANSL>AF.good</TRANSL>
                <TRANSL ver="zh_gloss">主焦.好</TRANSL>
            </M>
        </W>
        <W id="S11W4">
            <FORM>si</FORM>
            <M id="S11W4M0_0">
                <FORM>si</FORM>
                <TRANSL>say</TRANSL>
                <TRANSL ver="zh_gloss">說</TRANSL>
            </M>
        </W>
    </S>
    <S id="S_12">
        <FORM>ma meniq ka rupun si o.</FORM>
        <TRANSL xml:lang="zh"> 那麼我們另外一個缺齒的族規的話，</TRANSL>
        <TRANSL xml:lang="en"> And as for another custom, extracting (canine) teeth,</TRANSL>
        <W id="S12W0">
            <FORM>ma==</FORM>
            <M id="S12W0M0_0">
                <FORM>ma==</FORM>
                <TRANSL>FIL</TRANSL>
                <TRANSL ver="zh_gloss">FIL</TRANSL>
            </M>
        </W>
        <W id="S12W1">
            <FORM>m-eniq</FORM>
            <M id="S12W1M0_0">
                <FORM>m</FORM>
                <TRANSL>AF</TRANSL>
                <TRANSL ver="zh_gloss">主焦</TRANSL>
            </M>
            <M id="S12W1M1_0">
                <FORM>eniq</FORM>
                <TRANSL>be.at</TRANSL>
                <TRANSL ver="zh_gloss">在</TRANSL>
            </M>
        </W>
        <W id="S12W2">
            <FORM>ka</FORM>
            <M id="S12W2M0_0">
                <FORM>ka</FORM>
                <TRANSL>NOM</TRANSL>
                <TRANSL ver="zh_gloss">主格</TRANSL>
            </M>
        </W>
        <W id="S12W3">
            <FORM>rupun</FORM>
            <M id="S12W3M0_0">
                <FORM>rupun</FORM>
                <TRANSL>tooth</TRANSL>
                <TRANSL ver="zh_gloss">牙</TRANSL>
            </M>
        </W>
        <W id="S12W4">
            <FORM>si</FORM>
            <M id="S12W4M0_0">
                <FORM>si</FORM>
                <TRANSL>say</TRANSL>
                <TRANSL ver="zh_gloss">說</TRANSL>
            </M>
        </W>
        <W id="S12W5">
            <FORM>o==</FORM>
            <M id="S12W5M0_0">
                <FORM>o==</FORM>
                <TRANSL>FIL</TRANSL>
                <TRANSL ver="zh_gloss">FIL</TRANSL>
            </M>
        </W>
    </S>
    <S id="S_13">
        <FORM>kirei qitaan ka rupun uri o angalan waqi mesa ka rudan cbeyo.</FORM>
        <TRANSL xml:lang="zh"> 我們把犬齒拔掉，看起來也是很漂亮的，我們的祖先是這麼說的。</TRANSL>
        <TRANSL xml:lang="en"> Our ancestors said that we look beautiful after we extract our canine teeth.</TRANSL>
        <W id="S13W0">
            <FORM>&lt;L2JkireiL2J&gt;</FORM>
            <M id="S13W0M0_0">
                <FORM>&lt;L2JkireiL2J&gt;</FORM>
                <TRANSL>beautiful</TRANSL>
                <TRANSL ver="zh_gloss">漂亮</TRANSL>
            </M>
        </W>
        <W id="S13W1">
            <FORM>qita-an</FORM>
            <M id="S13W1M0_0">
                <FORM>qita</FORM>
                <TRANSL>look</TRANSL>
                <TRANSL ver="zh_gloss">看</TRANSL>
            </M>
            <M id="S13W1M1_0">
                <FORM>an</FORM>
                <TRANSL>LF</TRANSL>
                <TRANSL ver="zh_gloss">處焦</TRANSL>
            </M>
        </W>
        <W id="S13W2">
            <FORM>ka</FORM>
            <M id="S13W2M0_0">
                <FORM>ka</FORM>
                <TRANSL>NOM</TRANSL>
                <TRANSL ver="zh_gloss">主格</TRANSL>
            </M>
        </W>
        <W id="S13W3">
            <FORM>rupun</FORM>
            <M id="S13W3M0_0">
                <FORM>rupun</FORM>
                <TRANSL>tooth</TRANSL>
                <TRANSL ver="zh_gloss">牙</TRANSL>
            </M>
        </W>
        <W id="S13W4">
            <FORM>uri</FORM>
            <M id="S13W4M0_0">
                <FORM>uri</FORM>
                <TRANSL>also</TRANSL>
                <TRANSL ver="zh_gloss">也</TRANSL>
            </M>
        </W>
        <W id="S13W5">
            <FORM>o</FORM>
            <M id="S13W5M0_0">
                <FORM>o</FORM>
                <TRANSL>FIL</TRANSL>
                <TRANSL ver="zh_gloss">FIL</TRANSL>
            </M>
        </W>
        <W id="S13W6">
            <FORM>angal-an</FORM>
            <M id="S13W6M0_0">
                <FORM>angal</FORM>
                <TRANSL>take</TRANSL>
                <TRANSL ver="zh_gloss">拿</TRANSL>
            </M>
            <M id="S13W6M1_0">
                <FORM>an</FORM>
                <TRANSL>LF</TRANSL>
                <TRANSL ver="zh_gloss">處焦</TRANSL>
            </M>
        </W>
        <W id="S13W7">
            <FORM>waqi</FORM>
            <M id="S13W7M0_0">
                <FORM>waqi</FORM>
                <TRANSL>bucktooth</TRANSL>
                <TRANSL ver="zh_gloss">獠牙</TRANSL>
            </M>
        </W>
        <W id="S13W8">
            <FORM>mesa</FORM>
            <M id="S13W8M0_0">
                <FORM>mesa</FORM>
                <TRANSL>AF.say</TRANSL>
                <TRANSL ver="zh_gloss">主焦.說</TRANSL>
            </M>
        </W>
        <W id="S13W9">
            <FORM>ka</FORM>
            <M id="S13W9M0_0">
                <FORM>ka</FORM>
                <TRANSL>NOM</TRANSL>
                <TRANSL ver="zh_gloss">主格</TRANSL>
            </M>
        </W>
        <W id="S13W10">
            <FORM>rudan</FORM>
            <M id="S13W10M0_0">
                <FORM>rudan</FORM>
                <TRANSL>elderly</TRANSL>
                <TRANSL ver="zh_gloss">長者</TRANSL>
            </M>
        </W>
        <W id="S13W11">
            <FORM>cbeyo</FORM>
            <M id="S13W11M0_0">
                <FORM>cbeyo</FORM>
                <TRANSL>past</TRANSL>
                <TRANSL ver="zh_gloss">以前</TRANSL>
            </M>
        </W>
    </S>
    <S id="S_14">
        <FORM>a so uh kiya naq da.</FORM>
        <TRANSL xml:lang="zh"> 啊，就是這樣而已了。</TRANSL>
        <TRANSL xml:lang="en"> Ah! That's all.</TRANSL>
        <W id="S14W0">
            <FORM>a</FORM>
            <M id="S14W0M0_0">
                <FORM>a</FORM>
                <TRANSL>INT</TRANSL>
                <TRANSL ver="zh_gloss">感嘆</TRANSL>
            </M>
        </W>
        <W id="S14W1">
            <FORM>so</FORM>
            <M id="S14W1M0_0">
                <FORM>so</FORM>
                <TRANSL>be.like.this</TRANSL>
                <TRANSL ver="zh_gloss">像這樣</TRANSL>
            </M>
        </W>
        <W id="S14W2">
            <FORM>uh</FORM>
            <M id="S14W2M0_0">
                <FORM>uh</FORM>
                <TRANSL>FIL</TRANSL>
                <TRANSL ver="zh_gloss">FIL</TRANSL>
            </M>
        </W>
        <W id="S14W3">
            <FORM>kiya</FORM>
            <M id="S14W3M0_0">
                <FORM>kiya</FORM>
                <TRANSL>that</TRANSL>
                <TRANSL ver="zh_gloss">那個</TRANSL>
            </M>
        </W>
        <W id="S14W4">
            <FORM>naq</FORM>
            <M id="S14W4M0_0">
                <FORM>naq</FORM>
                <TRANSL>self</TRANSL>
                <TRANSL ver="zh_gloss">自己</TRANSL>
            </M>
        </W>
        <W id="S14W5">
            <FORM>da</FORM>
            <M id="S14W5M0_0">
                <FORM>da</FORM>
                <TRANSL>PFV.PART</TRANSL>
                <TRANSL ver="zh_gloss">完成.語助詞</TRANSL>
            </M>
        </W>
    </S>
</TEXT>
