<?xml version="1.0" ?>
<TEXT id="Wiki_Atayal_Bruce_Altman" xml:lang="tay" source="Atayal Wikipedia, article: Bruce_Altman" copyright="CC BY-SA" citation="Bruce_Altman. (2025, May 05). In Wikipedia [Atayal]. https://tay.wikipedia.org/wiki/Bruce_Altman" BibTeX_citation="@misc{Wiki_tay_Bruce_Altman, title = Bruce_Altman, year = 2025, month = May, day = 5, note = {In Wikipedia [Atayal]}, url = {https://tay.wikipedia.org/wiki/Bruce_Altman} }">
    <S id="0">
        <FORM kindOf="original">Bruce Altman htgan na ryax 1955 kawas 7 byacing 3 ryax. tmasot mqbaq biru beh Yale School of Drama. qyanux na sraral 1972 kawas htgan na ryax maki The Bronx, New York. Bruce Altman maki yotay squilq puqing ramu. cinkhulan sa knita' sa brbiru' Lists of actors</FORM>
        <FORM kindOf="standard">Bruce Altman htgan na ryax 1955 kawas 7 byacing 3 ryax. tmasot mqbaq biru beh Yale School of Drama. qyanux na sraral 1972 kawas htgan na ryax maki The Bronx, New York. Bruce Altman maki yotay squilq puqing ramu. cinkhulan sa knita' sa brbiru' Lists of actors</FORM>
        <PHON kindOf="standard">βruʦ~ʨe altman ħtɣan na rjax **** kawas~ɕ * βjaʦ~ʨiŋ * rjax. tmas~ɕot mqβaq βiru βeħ jale s~ɕʦ~ʨħool o* *rama. qjanux na s~ɕraral **** kawas~ɕ ħtɣan na rjax maki tħe βronx, new jork. βruʦ~ʨe altman maki jotaj s~ɕquilq puqiŋ ramu. ʦ~ʨinkħulan s~ɕa knitaʔ s~ɕa βrβiruʔ lis~ɕts~ɕ o* aʦ~ʨtors~ɕ</PHON>
    </S>
</TEXT>