<?xml version="1.0" ?>
<TEXT id="Wiki_Sakizaya_Bruce_Bowen" xml:lang="szy" source="Sakizaya Wikipedia, article: Bruce_Bowen" copyright="CC BY-SA" citation="Wikipedia contributors. (2026). Sakizaya Wikipedia. Wikimedia Foundation. Retrieved 2026-06-09, from https://szy.wikipedia.org/" BibTeX_citation="@misc{Wiki_szy, title = {Sakizaya Wikipedia}, author = {{Wikipedia contributors}}, year = {2026}, publisher = {Wikimedia Foundation}, url = {https://szy.wikipedia.org/}, urldate = {2026-06-09} }">
    <S id="0">
        <FORM kindOf="original">Bruce Bowen nalecuhan i Merced, California, nanu syubay kanas-mali miunduay nu Amilika NBA nisakaput, pahanhanan tu kawaw ayza. 6 bulad 14 demiad, 1971 a mihca, Bruce Bowen, miunduay.</FORM>
        <PHON kindOf="original">bruʦə bowən nar~ɾəʦuħan i mərʦəd, ʦar~ɾifornia, nanu sjubaj kanas-mar~ɾi miunduaj nu amir~ɾika nba nisakaput, paħanħanan tu kawaw ajza. * bur~ɾad ** dəmiad, **** a miħʦa, bruʦə bowən, miunduaj.</PHON>
        <FORM kindOf="standard">Bruce Bowen nalecuhan i Merced, California, nanu syubay kanas-mali miunduay nu Amilika NBA nisakaput, pahanhanan tu kawaw ayza. 6 bulad 14 demiad, 1971 a mihca, Bruce Bowen, miunduay.</FORM>
        <PHON kindOf="standard">bruʦə bowən nar~ɾəʦuħan i mərʦəd, ʦar~ɾifornia, nanu sjubaj kanas-mar~ɾi miunduaj nu amir~ɾika nba nisakaput, paħanħanan tu kawaw ajza. * bur~ɾad ** dəmiad, **** a miħʦa, bruʦə bowən, miunduaj.</PHON>
    </S>
</TEXT>