<?xml version="1.0" ?>
<TEXT id="NTU_Stry_Paiwan_Y2_one_minute_spontaneous_speech_self_introduction_wuh01" xml:lang="pwn" source="NTU Corpus, Paiwan, Y2 one-minute spontaneous speech; source EAF: self-introduction_wuh01 1 min.eaf; anonymized speaker label: wuh01" audio="self-introduction_wuh01.wav" dialect="Eastern Paiwan" copyright="" citation="" BibTeX_citation="">
    <S id="Y2_self_introduction_wuh01_S1">
        <FORM>ljakua avan auta bukesi aken.</FORM>
        <AUDIO start="52.479" end="55.32"/>
    </S>
    <S id="Y2_self_introduction_wuh01_S2">
        <FORM>izua aicu a na matucu a ku sengsengan auta i ta imaza i kuikai, malaing tu inu.</FORM>
        <AUDIO start="55.73" end="60.983"/>
    </S>
    <S id="Y2_self_introduction_wuh01_S3">
        <FORM>izua a salinga e pusaladjan ku paqeljingan tiamadju.</FORM>
        <AUDIO start="60.983" end="66.42"/>
    </S>
    <S id="Y2_self_introduction_wuh01_S4">
        <FORM>sa a niaken a qinaljan imaza i singding aicu a i singding a mavan a izua anan a dripung ta zua e pinisetjavat imaza i lizuk.</FORM>
        <AUDIO start="67.211" end="82.9"/>
    </S>
    <S id="Y2_self_introduction_wuh01_S5">
        <FORM>a ia anan a e kisepuliv a dripung ta zua, imaza anga nia matjeljaljak a nia tjay sangasangas imaza i singyuen.</FORM>
        <AUDIO start="82.9" end="95.115"/>
    </S>
    <S id="Y2_self_introduction_wuh01_S6">
        <FORM>sa tucu e izua anga aicu a e ngadan imaza i ta siuhu e aicu a nia qinaljan.</FORM>
        <AUDIO start="95.115" end="104.455"/>
    </S>
    <S id="Y2_self_introduction_wuh01_S7">
        <FORM>sa aicu a nia qinaljan, e matjesepatj aicu a kemasizi e e tjagaraus a a i vavua qinaljan a na sevalit a na izua sema maza i imaza i lizuk i singding.</FORM>
        <AUDIO start="104.455" end="121.003"/>
    </S>
</TEXT>
