<?xml version="1.0" ?>
<TEXT id="20200115_bufangwen_MVI_2303" xml:lang="tay" dialect="Sekolik" audio="https://www.youtube.com/watch?v=7ODoONfC89Q" source="Wilang Yutas Atayal Videos" copyright="CC-BY-NC" citation="" BibTeX_citation="">
    <S id="Atayal_1">
        <FORM kindOf="original" notes="multiple speakers">aw, a~mama pqutay misu cikay ki. aw, a.. swa' su son nha mah balay ga lalu su ga Wilang ha rwa.</FORM>
        <PHON kindOf="original">aw, a~mama pqutaj misu  ¶ikaj ki. aw, a.. swa Ē su son nńßa mańß ő≤~valaj …£a lalu su …£a wilaŇč ńßa rwa.</PHON>
        <FORM kindOf="standard" notes="multiple speakers">aw, a~mama pqutay misu cikay ki. aw, a.. swa' su son nha mah balay ga lalu su ga Wilang ha rwa.</FORM>
        <PHON kindOf="standard">aw, a~mama pqutaj mis~…ēu  ¶~ ®ikaj ki. aw, a.. s~…ēwa Ē s~…ēu s~…ēon nńßa mańß ő≤alaj …£a lalu s~…ēu …£a wilaŇč ńßa rwa.</PHON>
        <AUDIO start="0.96" end="8.52" file="20200115_bufangwen_MVI_2303_Atayal_1.wav"/>
    </S>
    <S id="Atayal_2">
        <FORM kindOf="original" notes="multiple speakers">aw. kmayal su mha muci soni ga, e aring su hetay mwah su hetay, mwah su ngasal lga.</FORM>
        <PHON kindOf="original">aw. kmajal su mńßa mu ¶i soni …£a, e ariŇč su ńßetaj mwańß su ńßetaj, mwańß su Ňčasal l…£a.</PHON>
        <FORM kindOf="standard" notes="multiple speakers">aw. kmayal su mha muci soni ga, e aring su hetay mwah su hetay, mwah su ngasal lga.</FORM>
        <PHON kindOf="standard">aw. kmajal s~…ēu mńßa mu ¶~ ®i s~…ēoni …£a, e ariŇč s~…ēu ńßetaj mwańß s~…ēu ńßetaj, mwańß s~…ēu Ňčas~…ēal l…£a.</PHON>
        <AUDIO start="8.52" end="15.56" file="20200115_bufangwen_MVI_2303_Atayal_2.wav"/>
    </S>
    <S id="Atayal_3">
        <FORM kindOf="original" notes="multiple speakers">biqan us nha Maci rwa. a. swa su nha son Maci lozi.</FORM>
        <PHON kindOf="original">ő≤~viqan us nńßa ma ¶i rwa. a. swa su nńßa son ma ¶i lozi.</PHON>
        <FORM kindOf="standard" notes="multiple speakers">biqan us nha Maci rwa. a. swa su nha son Maci lozi.</FORM>
        <PHON kindOf="standard">ő≤iqan us~…ē nńßa ma ¶~ ®i rwa. a. s~…ēwa s~…ēu nńßa s~…ēon ma ¶~ ®i lozi.</PHON>
        <AUDIO start="15.56" end="21.0" file="20200115_bufangwen_MVI_2303_Atayal_3.wav"/>
    </S>
    <S id="Atayal_4">
        <FORM kindOf="original" notes="multiple speakers">aw, Maci' qanoi ga, mnwah ku hetay lga, mwah ku qmalup qalang musa ku mluw kya qalang uzi pi. aw.</FORM>
        <PHON kindOf="original">aw, ma ¶i Ē qanoi …£a, mnwańß ku ńßetaj l…£a, mwańß ku qmalup qalaŇč musa ku mluw kja qalaŇč uzi pi. aw.</PHON>
        <FORM kindOf="standard" notes="multiple speakers">aw, Maci' qanoi ga, mnwah ku hetay lga, mwah ku qmalup qalang musa ku mluw kya qalang uzi pi. aw.</FORM>
        <PHON kindOf="standard">aw, ma ¶~ ®i Ē qanoi …£a, mnwańß ku ńßetaj l…£a, mwańß ku qmalup qalaŇč mus~…ēa ku mluw kja qalaŇč uzi pi. aw.</PHON>
        <AUDIO start="21.0" end="27.4" file="20200115_bufangwen_MVI_2303_Atayal_4.wav"/>
    </S>
    <S id="Atayal_5">
        <FORM kindOf="original" notes="multiple speakers">mu' mit lga. ne. m.. tlequn nha kya lga. sanme</FORM>
        <PHON kindOf="original">mu Ē mit l…£a. ne. m.. tlequn nńßa kja l…£a. sanme</PHON>
        <FORM kindOf="standard" notes="multiple speakers">mu' mit lga. ne. m.. tlequn nha kya lga. sanme</FORM>
        <PHON kindOf="standard">mu Ē mit l…£a. ne. m.. tlequn nńßa kja l…£a. s~…ēanme</PHON>
        <AUDIO start="27.4" end="33.06" file="20200115_bufangwen_MVI_2303_Atayal_5.wav"/>
    </S>
    <S id="Atayal_6">
        <FORM kindOf="original">ktan lga ne o~</FORM>
        <PHON kindOf="original">ktan l…£a ne o~</PHON>
        <FORM kindOf="standard">ktan lga ne o~</FORM>
        <PHON kindOf="standard">ktan l…£a ne o~</PHON>
        <AUDIO start="33.06" end="36.8" file="20200115_bufangwen_MVI_2303_Atayal_6.wav"/>
    </S>
    <S id="Atayal_7">
        <FORM kindOf="original" notes="multiple speakers">si tbuci' toh toh son nha bbtunux rwa. aw. bnkis</FORM>
        <PHON kindOf="original">si tő≤~vu ¶i Ē tońß tońß son nńßa ő≤~vő≤~vtunux rwa. aw. ő≤~vnkis</PHON>
        <FORM kindOf="standard" notes="multiple speakers">si tbuci' toh toh son nha bbtunux rwa. aw. bnkis</FORM>
        <PHON kindOf="standard">s~…ēi tő≤u ¶~ ®i Ē tońß tońß s~…ēon nńßa ő≤ő≤tunux rwa. aw. ő≤nkis~…ē</PHON>
        <AUDIO start="36.8" end="41.7" file="20200115_bufangwen_MVI_2303_Atayal_7.wav"/>
    </S>
    <S id="Atayal_8">
        <FORM kindOf="original">tlami son mu, wi!swa simu bsyaq balay</FORM>
        <PHON kindOf="original">tlami son mu, wi!swa simu ő≤~vsjaq ő≤~valaj</PHON>
        <FORM kindOf="standard">tlami son mu, wi!swa simu bsyaq balay</FORM>
        <PHON kindOf="standard">tlami s~…ēon mu, wi!s~…ēwa s~…ēimu ő≤s~…ējaq ő≤alaj</PHON>
        <AUDIO start="41.7" end="45.78" file="20200115_bufangwen_MVI_2303_Atayal_8.wav"/>
    </S>
    <S id="Atayal_9">
        <FORM kindOf="original">thzyaq uzi pi. ktan ga wey. musa ku mhkangi</FORM>
        <PHON kindOf="original">tńßzjaq uzi pi. ktan …£a wej. musa ku mńßkaŇči</PHON>
        <FORM kindOf="standard">thzyaq uzi pi. ktan ga wey. musa ku mhkangi</FORM>
        <PHON kindOf="standard">tńßzjaq uzi pi. ktan …£a wej. mus~…ēa ku mńßkaŇči</PHON>
        <AUDIO start="45.78" file="20200115_bufangwen_MVI_2303_Atayal_9.wav"/>
    </S>
</TEXT>