<?xml version='1.0' encoding='UTF-8'?>
<TEXT id="NTU_Pwn_Orsen_02 Orsen 12" xml:lang="pwn" source="NTU Paiwan Data, Participant Orsen, file 02 Orsen 12" audio="02_Orsen_12.wav" copyright="CC-BY" citation="Le Ferrand, √Č., Prud'hommeaux, E., Hartshorne, J. K., &amp; Sung, L.-M. (2024). NTU Paiwan ASR Corpus. Electronic Resource." BibTeX_citation="@electronic{leferrand2024ntu, author = {Le Ferrand, {\'E}ric and Prud'hommeaux, Emily and Hartshorne, Joshua K. and Sung, Li-May}, year = {2024}, title = {{NTU} {Paiwan} {ASR} Corpus},type = {Electronic Resource}}" dialect="Southern">
    <S id="a1">
        <FORM kindOf="original">ta sicuayan izua a qinaljan i pasanavalj a semamalji. a sinanpalisi nua se Sabediq a caucau. azua qinaljan i dungdung tua izua cekes a qinaljan. saka i palaulauz tua gimeng a sicuayan.</FORM>
        <PHON kindOf="original">ta si ¶uajan izua a qina éan i pasanava é a s…ômama éi. a sinanpa…£isi nua s…ô sab…ôdiq a  ¶au ¶au. azua qina éan i duŇčduŇč tua izua  ¶…ôk…ôs a qina éan. saka i pa…£au…£auz tua gim…ôŇč a si ¶uajan.</PHON>
        <FORM kindOf="standard">ta sicuayan izua a qinaljan i pasanavalj a semamalji. a sinanpalisi nua se Sabediq a caucau. azua qinaljan i dungdung tua izua cekes a qinaljan. saka i palaulauz tua gimeng a sicuayan.</FORM>
        <PHON kindOf="standard">ta si ¶uajan izua a qina éan i pasanava é a s…ômama éi. a sinanpa…£isi nua s…ô sab…ôdiq a  ¶au ¶au. azua qina éan i duŇčduŇč tua izua  ¶…ôk…ôs a qina éan. saka i pa…£au…£auz tua gim…ôŇč a si ¶uajan.</PHON>
        <AUDIO start="2.400" end="19.450" file="02_Orsen_12_a1.wav"/>
    </S>
    <S id="a2">
        <FORM kindOf="original">tucu cemecemelanga. azua qinaljan pinapungadan tu Djiraw. aku sinanpalisi aravac. namaitucu a tjaucikel nua ramaljemaljeng.</FORM>
        <PHON kindOf="original">tu ¶u  ¶…ôm…ô ¶…ôm…ô…£aŇča. azua qina éan pinapuŇčadan tu …ČiRaw. aku sinanpa…£isi aRava ¶. namaitu ¶u a  ¶au ¶ik…ô…£ nua Rama é…ôma é…ôŇč.</PHON>
        <FORM kindOf="standard">tucu cemecemelanga. azua qinaljan pinapungadan tu Djiraw. aku sinanpalisi aravac. namaitucu a tjaucikel nua ramaljemaljeng.</FORM>
        <PHON kindOf="standard">tu ¶u  ¶…ôm…ô ¶…ôm…ô…£aŇča. azua qina éan pinapuŇčadan tu …ČiRaw. aku sinanpa…£isi aRava ¶. namaitu ¶u a  ¶au ¶ik…ô…£ nua Rama é…ôma é…ôŇč.</PHON>
        <AUDIO start="20.570" end="32.910" file="02_Orsen_12_a2.wav"/>
    </S>
    <S id="a3">
        <FORM kindOf="original">azua i Djiraw a qinaljan. lja Kivali katua Piraljung a naqemiladj i zua. nakemasiviri a se Paiwan tiamadju.</FORM>
        <PHON kindOf="original">azua i …ČiRaw a qina éan.  éa kiva…£i katua piRa éuŇč a naq…ômi…£a…Č i zua. nak…ômasiviRi a s…ô paiwan tiama…Ču.</PHON>
        <FORM kindOf="standard">azua i Djiraw a qinaljan. lja Kivali katua Piraljung a naqemiladj i zua. nakemasiviri a se Paiwan tiamadju.</FORM>
        <PHON kindOf="standard">azua i …ČiRaw a qina éan.  éa kiva…£i katua piRa éuŇč a naq…ômi…£a…Č i zua. nak…ômasiviRi a s…ô paiwan tiama…Ču.</PHON>
        <AUDIO start="33.950" end="46.110" file="02_Orsen_12_a3.wav"/>
    </S>
    <S id="a4">
        <FORM kindOf="original">natjemavat a mazua i Djiraw. tiamadju avan a caucau nua Seqalu. nu pacalja tiamadju. pasazua i zua mamazangiljan a lja Taligu nua Seqalu.</FORM>
        <PHON kindOf="original">na ¶…ômavat a mazua i …ČiRaw. tiama…Ču avan a  ¶au ¶au nua s…ôqa…£u. nu pa ¶a éa tiama…Ču. pasazua i zua mamazaŇči éan a  éa ta…£igu nua s…ôqa…£u.</PHON>
        <FORM kindOf="standard">natjemavat a mazua i Djiraw. tiamadju avan a caucau nua Seqalu. nu pacalja tiamadju. pasazua i zua mamazangiljan a lja Taligu nua Seqalu.</FORM>
        <PHON kindOf="standard">na ¶…ômavat a mazua i …ČiRaw. tiama…Ču avan a  ¶au ¶au nua s…ôqa…£u. nu pa ¶a éa tiama…Ču. pasazua i zua mamazaŇči éan a  éa ta…£igu nua s…ôqa…£u.</PHON>
        <AUDIO start="46.660" end="60.200" file="02_Orsen_12_a4.wav"/>
    </S>
    <S id="a5">
        <FORM kindOf="original">tazua navaik a kika sacemel a uqaljaqaljay. amin a ramaljemaljeng vavayavayan kata kakedrian a i qinaljan.</FORM>
        <PHON kindOf="original">tazua navaik a kika sa ¶…ôm…ô…£ a uqa éaqa éaj. amin a Rama é…ôma é…ôŇč vavajavajan kata kak…ô…Ėian a i qina éan.</PHON>
        <FORM kindOf="standard">tazua navaik a kika sacemel a uqaljaqaljay. amin a ramaljemaljeng vavayavayan kata kakedrian a i qinaljan.</FORM>
        <PHON kindOf="standard">tazua navaik a kika sa ¶…ôm…ô…£ a uqa éaqa éaj. amin a Rama é…ôma é…ôŇč vavajavajan kata kak…ô…Ėian a i qina éan.</PHON>
        <AUDIO start="61.030" end="70.560" file="02_Orsen_12_a5.wav"/>
    </S>
    <S id="a6">
        <FORM kindOf="original">manu azua Seqalu katua se Vuljavuljau a pairang masudju tiamadju. sa qaluin a kivuruvuru a mazua i Djiraw. ljamain a tapaw sa qeciin tiamadju a mapuljat.</FORM>
        <PHON kindOf="original">manu azua s…ôqa…£u katua s…ô vu éavu éau a paiRaŇč masu…Ču tiama…Ču. sa qa…£uin a kivuRuvuRu a mazua i …ČiRaw.  éamain a tapaw sa q…ô ¶iin tiama…Ču a mapu éat.</PHON>
        <FORM kindOf="standard">manu azua Seqalu katua se Vuljavuljau a pairang masudju tiamadju. sa qaluin a kivuruvuru a mazua i Djiraw. ljamain a tapaw sa qeciin tiamadju a mapuljat.</FORM>
        <PHON kindOf="standard">manu azua s…ôqa…£u katua s…ô vu éavu éau a paiRaŇč masu…Ču tiama…Ču. sa qa…£uin a kivuRuvuRu a mazua i …ČiRaw.  éamain a tapaw sa q…ô ¶iin tiama…Ču a mapu éat.</PHON>
        <AUDIO start="71.090" end="86.750" file="02_Orsen_12_a6.wav"/>
    </S>
    <S id="a7">
        <FORM kindOf="original">patjemangetjezanga azua uqaljaqaljay a nakisacemel. pacunan a qinaljan a namaljama. namacayanga a mapuljat a sikataqaljan.</FORM>
        <PHON kindOf="original">pa ¶…ômaŇč…ô ¶…ôzaŇča azua uqa éaqa éaj a nakisa ¶…ôm…ô…£. pa ¶unan a qina éan a nama éama. nama ¶ajaŇča a mapu éat a sikataqa éan.</PHON>
        <FORM kindOf="standard">patjemangetjezanga azua uqaljaqaljay a nakisacemel. pacunan a qinaljan a namaljama. namacayanga a mapuljat a sikataqaljan.</FORM>
        <PHON kindOf="standard">pa ¶…ômaŇč…ô ¶…ôzaŇča azua uqa éaqa éaj a nakisa ¶…ôm…ô…£. pa ¶unan a qina éan a nama éama. nama ¶ajaŇča a mapu éat a sikataqa éan.</PHON>
        <AUDIO start="87.550" end="97.890" file="02_Orsen_12_a7.wav"/>
    </S>
    <S id="a8">
        <FORM kindOf="original">qemaung sa pakivadaq tua pulingaw tu kemuda tiamadju a pavalet. manu papuvarungen azua pulingaw. sa qivu a maitucu. aicu a Seqalu napuqizing napupicul aravac.</FORM>
        <PHON kindOf="original">q…ômauŇč sa pakivadaq tua pu…£iŇčaw tu k…ômuda tiama…Ču a pava…£…ôt. manu papuvaRuŇč…ôn azua pu…£iŇčaw. sa qivu a maitu ¶u. ai ¶u a s…ôqa…£u napuqiziŇč napupi ¶u…£ aRava ¶.</PHON>
        <FORM kindOf="standard">qemaung sa pakivadaq tua pulingaw tu kemuda tiamadju a pavalet. manu papuvarungen azua pulingaw. sa qivu a maitucu. aicu a Seqalu napuqizing napupicul aravac.</FORM>
        <PHON kindOf="standard">q…ômauŇč sa pakivadaq tua pu…£iŇčaw tu k…ômuda tiama…Ču a pava…£…ôt. manu papuvaRuŇč…ôn azua pu…£iŇčaw. sa qivu a maitu ¶u. ai ¶u a s…ôqa…£u napuqiziŇč napupi ¶u…£ aRava ¶.</PHON>
        <AUDIO start="98.300" end="115.260" file="02_Orsen_12_a8.wav"/>
    </S>
    <S id="a9">
        <FORM kindOf="original">inika uri pakaqeci mun aya. au saqetju a varung niamadju. qemauqaung tua neka nu picul a uri kiqecev tua Seqalu. manu kanen a me penuljat na za kuwa. sa maqulipanga azua qinaljan.</FORM>
        <PHON kindOf="original">inika uRi pakaq…ô ¶i mun aja. au saq…ô ¶u a vaRuŇč niama…Ču. q…ômauqauŇč tua n…ôka nu pi ¶u…£ a uRi kiq…ô ¶…ôv tua s…ôqa…£u. manu kan…ôn a m…ô p…ônu éat na za kuwa. sa maqu…£ipaŇča azua qina éan.</PHON>
        <FORM kindOf="standard">inika uri pakaqeci mun aya. au saqetju a varung niamadju. qemauqaung tua neka nu picul a uri kiqecev tua Seqalu. manu kanen a me penuljat na za kuwa. sa maqulipanga azua qinaljan.</FORM>
        <PHON kindOf="standard">inika uRi pakaq…ô ¶i mun aja. au saq…ô ¶u a vaRuŇč niama…Ču. q…ômauqauŇč tua n…ôka nu pi ¶u…£ a uRi kiq…ô ¶…ôv tua s…ôqa…£u. manu kan…ôn a m…ô p…ônu éat na za kuwa. sa maqu…£ipaŇča azua qina éan.</PHON>
        <AUDIO start="115.600" end="134.000" file="02_Orsen_12_a9.wav"/>
    </S>
    <S id="a10">
        <FORM kindOf="original">tu sika patjetucu neka temuru a semazua. kemasicuay napapaulingaw aravac a tja ramaljeng. maya semazua. ini bulay a kadjunangan izua aya.</FORM>
        <PHON kindOf="original">tu sika pa ¶…ôtu ¶u n…ôka t…ômuRu a s…ômazua. k…ômasi ¶uaj napapau…£iŇčaw aRava ¶ a  ¶a Rama é…ôŇč. maja s…ômazua. ini bu…£aj a ka…ČunaŇčan izua aja.</PHON>
        <FORM kindOf="standard">tu sika patjetucu neka temuru a semazua. kemasicuay napapaulingaw aravac a tja ramaljeng. maya semazua. ini bulay a kadjunangan izua aya.</FORM>
        <PHON kindOf="standard">tu sika pa ¶…ôtu ¶u n…ôka t…ômuRu a s…ômazua. k…ômasi ¶uaj napapau…£iŇčaw aRava ¶ a  ¶a Rama é…ôŇč. maja s…ômazua. ini bu…£aj a ka…ČunaŇčan izua aja.</PHON>
        <AUDIO start="135.100" end="147.840" file="02_Orsen_12_a10.wav"/>
    </S>
    <S id="a11">
        <FORM kindOf="original">nu tja pacuan azua qinaljan. izua kudrakudral a qaciljay. samalji itjen tu 'asinu azua qaciljay. sa kemuda a qemalu a pasazua i qinaljan.</FORM>
        <PHON kindOf="original">nu  ¶a pa ¶uan azua qina éan. izua ku…Ėaku…Ėa…£ a qa ¶i éaj. sama éi i ¶…ôn tu  Ēasinu azua qa ¶i éaj. sa k…ômuda a q…ôma…£u a pasazua i qina éan.</PHON>
        <FORM kindOf="standard">nu tja pacuan azua qinaljan. izua kudrakudral a qaciljay. samalji itjen tu 'asinu azua qaciljay. sa kemuda a qemalu a pasazua i qinaljan.</FORM>
        <PHON kindOf="standard">nu  ¶a pa ¶uan azua qina éan. izua ku…Ėaku…Ėa…£ a qa ¶i éaj. sama éi i ¶…ôn tu  Ēasinu azua qa ¶i éaj. sa k…ômuda a q…ôma…£u a pasazua i qina éan.</PHON>
        <AUDIO start="148.670" end="161.590" file="02_Orsen_12_a11.wav"/>
    </S>
    <S id="a12">
        <FORM kindOf="original">ljaljepan namaitucu a qivu a ramaljemaljeng. a sicuayan izua qacaqaca a caucau a qemuziquzip a quziquzipen nua mamazangiljan.</FORM>
        <PHON kindOf="original"> éa é…ôpan namaitu ¶u a qivu a Rama é…ôma é…ôŇč. a si ¶uajan izua qa ¶aqa ¶a a  ¶au ¶au a q…ômuziquzip a quziquzip…ôn nua mamazaŇči éan.</PHON>
        <FORM kindOf="standard">ljaljepan namaitucu a qivu a ramaljemaljeng. a sicuayan izua qacaqaca a caucau a qemuziquzip a quziquzipen nua mamazangiljan.</FORM>
        <PHON kindOf="standard"> éa é…ôpan namaitu ¶u a qivu a Rama é…ôma é…ôŇč. a si ¶uajan izua qa ¶aqa ¶a a  ¶au ¶au a q…ômuziquzip a quziquzip…ôn nua mamazaŇči éan.</PHON>
        <AUDIO start="162.610" end="173.070" file="02_Orsen_12_a12.wav"/>
    </S>
    <S id="a13">
        <FORM kindOf="original">kimaya avananga zua rusakusakuc tua aicu a kudrakudral a qaciljay a pasazua i Djiraw. tu sisantapaw nua sikataqaljan.</FORM>
        <PHON kindOf="original">kimaja avanaŇča zua Rusakusaku ¶ tua ai ¶u a ku…Ėaku…Ėa…£ a qa ¶i éaj a pasazua i …ČiRaw. tu sisantapaw nua sikataqa éan.</PHON>
        <FORM kindOf="standard">kimaya avananga zua rusakusakuc tua aicu a kudrakudral a qaciljay a pasazua i Djiraw. tu sisantapaw nua sikataqaljan.</FORM>
        <PHON kindOf="standard">kimaja avanaŇča zua Rusakusaku ¶ tua ai ¶u a ku…Ėaku…Ėa…£ a qa ¶i éaj a pasazua i …ČiRaw. tu sisantapaw nua sikataqa éan.</PHON>
        <AUDIO start="173.360" end="185.020" file="02_Orsen_12_a13.wav"/>
    </S>
    <S id="a14">
        <FORM kindOf="original">aicu a tja qinaljan a sicuayan liyaw aravac namapulingetj i gadu. bulay itjen a kivadaq tua tja matjaljaljak tja vuvu. sa izua tja keljang tua tja qinaljan a sicuayan. amin.</FORM>
        <PHON kindOf="original">ai ¶u a  ¶a qina éan a si ¶uajan …£ijaw aRava ¶ namapu…£iŇč…ô ¶ i gadu. bu…£aj i ¶…ôn a kivadaq tua  ¶a ma ¶a éa éak  ¶a vuvu. sa izua  ¶a k…ô éaŇč tua  ¶a qina éan a si ¶uajan. amin.</PHON>
        <FORM kindOf="standard">aicu a tja qinaljan a sicuayan liyaw aravac namapulingetj i gadu. bulay itjen a kivadaq tua tja matjaljaljak tja vuvu. sa izua tja keljang tua tja qinaljan a sicuayan. amin.</FORM>
        <PHON kindOf="standard">ai ¶u a  ¶a qina éan a si ¶uajan …£ijaw aRava ¶ namapu…£iŇč…ô ¶ i gadu. bu…£aj i ¶…ôn a kivadaq tua  ¶a ma ¶a éa éak  ¶a vuvu. sa izua  ¶a k…ô éaŇč tua  ¶a qina éan a si ¶uajan. amin.</PHON>
        <AUDIO start="185.430" end="199.740" file="02_Orsen_12_a14.wav"/>
    </S>
</TEXT>
