<?xml version="1.0" ?>
<TEXT id="NTU_Pwn_Zendar_02JN112-2 Zendar" xml:lang="pwn" source="NTU Paiwan Data, Participant Zendar, file 02JN112-2 Zendar" audio="02JN112-2_Zendar.wav" copyright="CC-BY" citation="Le Ferrand, √Č., Prud'hommeaux, E., Hartshorne, J. K., &amp; Sung, L.-M. (2024). NTU Paiwan ASR Corpus. Electronic Resource." BibTeX_citation="@electronic{leferrand2024ntu, author = {Le Ferrand, {'E}ric and Prud'hommeaux, Emily and Hartshorne, Joshua K. and Sung, Li-May}, year = {2024}, title = {{NTU} {Paiwan} {ASR} Corpus},type = {Electronic Resource}}" dialect="Northern">
    <S id="a1">
        <FORM kindOf="original">kasicuayan, nu izua seman tjinukuyan i 'inaljan tua sepaiwan zuku, kipulju a ta'alja'aljan i 'inaljan a mapuljat.</FORM>
        <PHON kindOf="original">kasi ¶uajan, nu izua s…ôman  ¶inukujan i  Ēina éan tua s…ôpaiwan zuku, kipu éu a ta Ēa éa Ēa éan i  Ēina éan a mapu éat.</PHON>
        <FORM kindOf="standard">kasicuayan, nu izua seman tjinukuyan i 'inaljan tua sepaiwan zuku, kipulju a ta'alja'aljan i 'inaljan a mapuljat.</FORM>
        <PHON kindOf="standard">kasi ¶uajan, nu izua s…ôman  ¶inukujan i  Ēina éan tua s…ôpaiwan zuku, kipu éu a ta Ēa éa Ēa éan i  Ēina éan a mapu éat.</PHON>
        <AUDIO start="2.469" end="15.136" file="02JN112-2_Zendar_a1.wav"/>
    </S>
    <S id="a2">
        <FORM kindOf="original">tuazua tjaturuvuanan a 'emau a 'emuma'uma tua ta'alja'aljan, a patje tucu a patje seleman a tjinukuyan, neka nu pukaui a kipusengsengan a sema kavuavuan.</FORM>
        <PHON kindOf="original">tuazua  ¶aturuvuanan a  Ē…ômau a  Ē…ômuma Ēuma tua ta Ēa éa Ēa éan, a pa ¶…ô tu ¶u a pa ¶…ô s…ô…≠…ôman a  ¶inukujan, n…ôka nu pukaui a kipus…ôŇčs…ôŇčan a s…ôma kavuavuan.</PHON>
        <FORM kindOf="standard">tuazua tjaturuvuanan a 'emau a 'emuma'uma tua ta'alja'aljan, a patje tucu a patje seleman a tjinukuyan, neka nu pukaui a kipusengsengan a sema kavuavuan.</FORM>
        <PHON kindOf="standard">tuazua  ¶aturuvuanan a  Ē…ômau a  Ē…ômuma Ēuma tua ta Ēa éa Ēa éan, a pa ¶…ô tu ¶u a pa ¶…ô s…ô…≠…ôman a  ¶inukujan, n…ôka nu pukaui a kipus…ôŇčs…ôŇčan a s…ôma kavuavuan.</PHON>
        <AUDIO start="15.136" end="35.750" file="02JN112-2_Zendar_a2.wav"/>
    </S>
    <S id="a3">
        <FORM kindOf="original">azua ki makasimulu' a 'adaw, a i 'inaljan neka nu madjadjelidjeli, neka uta nu semenasenay, neka nu paraziuziu, neta uta nu pacucun tua tiribi.</FORM>
        <PHON kindOf="original">azua ki makasimu…≠u Ē a  Ēadaw, a i  Ēina éan n…ôka nu ma…Ča…Č…ô…≠i…Č…ô…≠i, n…ôka uta nu s…ôm…ônas…ônaj, n…ôka nu paraziuziu, n…ôta uta nu pa ¶u ¶un tua tiribi.</PHON>
        <FORM kindOf="standard">azua ki makasimulu' a 'adaw, a i 'inaljan neka nu madjadjelidjeli, neka uta nu semenasenay, neka nu paraziuziu, neta uta nu pacucun tua tiribi.</FORM>
        <PHON kindOf="standard">azua ki makasimu…≠u Ē a  Ēadaw, a i  Ēina éan n…ôka nu ma…Ča…Č…ô…≠i…Č…ô…≠i, n…ôka uta nu s…ôm…ônas…ônaj, n…ôka nu paraziuziu, n…ôta uta nu pa ¶u ¶un tua tiribi.</PHON>
        <AUDIO start="35.750" end="55.030" file="02JN112-2_Zendar_a3.wav"/>
    </S>
    <S id="a4">
        <FORM kindOf="original">&quot;aicu a tjapaulan a ta'alja'aljan a mapuljat, saka mama mamamawitjen a tasu kasuvetjevetjekan a kasu'ali'alian,&quot; ayaya a venarung a marka ta'alja'aljan,</FORM>
        <PHON kindOf="original">&quot;ai ¶u a  ¶apau…≠an a ta Ēa éa Ēa éan a mapu éat, saka mama mamamawi ¶…ôn a tasu kasuv…ô ¶…ôv…ô ¶…ôkan a kasu Ēa…≠i Ēa…≠ian,&quot; ajaja a v…ônaruŇč a marka ta Ēa éa Ēa éan,</PHON>
        <FORM kindOf="standard">&quot;aicu a tjapaulan a ta'alja'aljan a mapuljat, saka mama mamamawitjen a tasu kasuvetjevetjekan a kasu'ali'alian,&quot; ayaya a venarung a marka ta'alja'aljan,</FORM>
        <PHON kindOf="standard">&quot;ai ¶u a  ¶apau…≠an a ta Ēa éa Ēa éan a mapu éat, saka mama mamamawi ¶…ôn a tasu kasuv…ô ¶…ôv…ô ¶…ôkan a kasu Ēa…≠i Ēa…≠ian,&quot; ajaja a v…ônaruŇč a marka ta Ēa éa Ēa éan,</PHON>
        <AUDIO start="55.030" end="76.170" file="02JN112-2_Zendar_a4.wav"/>
    </S>
    <S id="a5">
        <FORM kindOf="original">manasika neka nu selaing a kipuneka a kisu kipuneka puvililjan a kipusau tazua vaivaik a kitjukuda a sikata'aljan.</FORM>
        <PHON kindOf="original">manasika n…ôka nu s…ô…≠aiŇč a kipun…ôka a kisu kipun…ôka puvi…≠i éan a kipusau tazua vaivaik a ki ¶ukuda a sikata Ēa éan.</PHON>
        <FORM kindOf="standard">manasika neka nu selaing a kipuneka a kisu kipuneka puvililjan a kipusau tazua vaivaik a kitjukuda a sikata'aljan.</FORM>
        <PHON kindOf="standard">manasika n…ôka nu s…ô…≠aiŇč a kipun…ôka a kisu kipun…ôka puvi…≠i éan a kipusau tazua vaivaik a ki ¶ukuda a sikata Ēa éan.</PHON>
        <AUDIO start="76.170" end="94.781" file="02JN112-2_Zendar_a5.wav"/>
    </S>
    <S id="a6">
        <FORM kindOf="original">izua za kai i tua seisiu a mayatucu, &quot;kisaseljangu a maleva tua maleva malevaleva a cawcau, kisaseljangu a 'emaung tua 'emau'aung a cawcau,&quot; aya</FORM>
        <PHON kindOf="original">izua za kai i tua s…ôisiu a majatu ¶u, &quot;kisas…ô éaŇču a ma…≠…ôva tua ma…≠…ôva ma…≠…ôva…≠…ôva a  ¶aw ¶au, kisas…ô éaŇču a  Ē…ômauŇč tua  Ē…ômau ĒauŇč a  ¶aw ¶au,&quot; aja</PHON>
        <FORM kindOf="standard">izua za kai i tua seisiu a mayatucu, &quot;kisaseljangu a maleva tua maleva malevaleva a cawcau, kisaseljangu a 'emaung tua 'emau'aung a cawcau,&quot; aya</FORM>
        <PHON kindOf="standard">izua za kai i tua s…ôisiu a majatu ¶u, &quot;kisas…ô éaŇču a ma…≠…ôva tua ma…≠…ôva ma…≠…ôva…≠…ôva a  ¶aw ¶au, kisas…ô éaŇču a  Ē…ômauŇč tua  Ē…ômau ĒauŇč a  ¶aw ¶au,&quot; aja</PHON>
        <AUDIO start="94.781" end="112.294" file="02JN112-2_Zendar_a6.wav"/>
    </S>
    <S id="a7">
        <FORM kindOf="original">mavan ka inianan ka kemljang a sepaiwan zuku a cawcau tua patjara cemas, ka inianan ka semupu tua seisiu, izua za izuanga za namayatucu a sivarungan.</FORM>
        <PHON kindOf="original">mavan ka inianan ka k…ôm éaŇč a s…ôpaiwan zuku a  ¶aw ¶au tua pa ¶ara  ¶…ômas, ka inianan ka s…ômupu tua s…ôisiu, izua za izuaŇča za namajatu ¶u a sivaruŇčan.</PHON>
        <FORM kindOf="standard">mavan ka inianan ka kemljang a sepaiwan zuku a cawcau tua patjara cemas, ka inianan ka semupu tua seisiu, izua za izuanga za namayatucu a sivarungan.</FORM>
        <PHON kindOf="standard">mavan ka inianan ka k…ôm éaŇč a s…ôpaiwan zuku a  ¶aw ¶au tua pa ¶ara  ¶…ômas, ka inianan ka s…ômupu tua s…ôisiu, izua za izuaŇča za namajatu ¶u a sivaruŇčan.</PHON>
        <AUDIO start="112.294" end="133.825" file="02JN112-2_Zendar_a7.wav"/>
    </S>
    <S id="a8">
        <FORM kindOf="original">a sinikitulu tua 'emaljup tua sepaiwan zuku a mareka ru'alju'aljup a cawcau ini ka manu sauru sauraman tua sacemel.</FORM>
        <PHON kindOf="original">a sinikitu…≠u tua  Ē…ôma éup tua s…ôpaiwan zuku a mar…ôka ru Ēa éu Ēa éup a  ¶aw ¶au ini ka manu sauru sauraman tua sa ¶…ôm…ô…≠.</PHON>
        <FORM kindOf="standard">a sinikitulu tua 'emaljup tua sepaiwan zuku a mareka ru'alju'aljup a cawcau ini ka manu sauru sauraman tua sacemel.</FORM>
        <PHON kindOf="standard">a sinikitu…≠u tua  Ē…ôma éup tua s…ôpaiwan zuku a mar…ôka ru Ēa éu Ēa éup a  ¶aw ¶au ini ka manu sauru sauraman tua sa ¶…ôm…ô…≠.</PHON>
        <AUDIO start="133.825" end="149.298" file="02JN112-2_Zendar_a8.wav"/>
    </S>
    <S id="a9">
        <FORM kindOf="original">a mareka raru'aljupan a cawcau tja tjaljaliavan a 'inaljup niamadju, ljakua palemek tu tjaljakedrikedrian a pinasuangalj nimadju niamadju tua inalap.</FORM>
        <PHON kindOf="original">a mar…ôka raru Ēa éupan a  ¶aw ¶au  ¶a  ¶a éa…≠iavan a  Ēina éup niama…Ču,  éakua pa…≠…ôm…ôk tu  ¶a éak…ô…Ėik…ô…Ėian a pinasuaŇča é nima…Ču niama…Ču tua ina…≠ap.</PHON>
        <FORM kindOf="standard">a mareka raru'aljupan a cawcau tja tjaljaliavan a 'inaljup niamadju, ljakua palemek tu tjaljakedrikedrian a pinasuangalj nimadju niamadju tua inalap.</FORM>
        <PHON kindOf="standard">a mar…ôka raru Ēa éupan a  ¶aw ¶au  ¶a  ¶a éa…≠iavan a  Ēina éup niama…Ču,  éakua pa…≠…ôm…ôk tu  ¶a éak…ô…Ėik…ô…Ėian a pinasuaŇča é nima…Ču niama…Ču tua ina…≠ap.</PHON>
        <AUDIO start="149.298" end="168.254" file="02JN112-2_Zendar_a9.wav"/>
    </S>
    <S id="a10">
        <FORM kindOf="original">kasicuayan, a mareka ru'alju'aljup nu izua inalap a sacemel, tjara vinadisan a pakaleva tua mamazangiljan, 'aw azua zumanga a vutjulj si sisiljevanga a 'emaru'arut tua ta'alja'aljan a pa pipaljing.</FORM>
        <PHON kindOf="original">kasi ¶uajan, a mar…ôka ru Ēa éu Ēa éup nu izua ina…≠ap a sa ¶…ôm…ô…≠,  ¶ara vinadisan a paka…≠…ôva tua mamazaŇči éan,  Ēaw azua zumaŇča a vu ¶u é si sisi é…ôvaŇča a  Ē…ômaru Ēarut tua ta Ēa éa Ēa éan a pa pipa éiŇč.</PHON>
        <FORM kindOf="standard">kasicuayan, a mareka ru'alju'aljup nu izua inalap a sacemel, tjara vinadisan a pakaleva tua mamazangiljan, 'aw azua zumanga a vutjulj si sisiljevanga a 'emaru'arut tua ta'alja'aljan a pa pipaljing.</FORM>
        <PHON kindOf="standard">kasi ¶uajan, a mar…ôka ru Ēa éu Ēa éup nu izua ina…≠ap a sa ¶…ôm…ô…≠,  ¶ara vinadisan a paka…≠…ôva tua mamazaŇči éan,  Ēaw azua zumaŇča a vu ¶u é si sisi é…ôvaŇča a  Ē…ômaru Ēarut tua ta Ēa éa Ēa éan a pa pipa éiŇč.</PHON>
        <AUDIO start="168.254" end="195.822" file="02JN112-2_Zendar_a10.wav"/>
    </S>
    <S id="a11">
        <FORM kindOf="original">ini ka amin nu izua a ma'ipe'ipel a kinacemkeljan i 'inaljan, azua mareka ru'alju'aljup a cawcau tjara sangasangas tjara sangasangasan sakamaya a sematjez tiamadju tazua sacemel a seman sinisupulju sinisupuljui sinisupulju.</FORM>
        <PHON kindOf="original">ini ka amin nu izua a ma Ēip…ô Ēip…ô…≠ a kina ¶…ômk…ô éan i  Ēina éan, azua mar…ôka ru Ēa éu Ēa éup a  ¶aw ¶au  ¶ara saŇčasaŇčas  ¶ara saŇčasaŇčasan sakamaja a s…ôma ¶…ôz tiama…Ču tazua sa ¶…ôm…ô…≠ a s…ôman sinisupu éu sinisupu éui sinisupu éu.</PHON>
        <FORM kindOf="standard">ini ka amin nu izua a ma'ipe'ipel a kinacemkeljan i 'inaljan, azua mareka ru'alju'aljup a cawcau tjara sangasangas tjara sangasangasan sakamaya a sematjez tiamadju tazua sacemel a seman sinisupulju sinisupuljui sinisupulju.</FORM>
        <PHON kindOf="standard">ini ka amin nu izua a ma Ēip…ô Ēip…ô…≠ a kina ¶…ômk…ô éan i  Ēina éan, azua mar…ôka ru Ēa éu Ēa éup a  ¶aw ¶au  ¶ara saŇčasaŇčas  ¶ara saŇčasaŇčasan sakamaja a s…ôma ¶…ôz tiama…Ču tazua sa ¶…ôm…ô…≠ a s…ôman sinisupu éu sinisupu éui sinisupu éu.</PHON>
        <AUDIO start="195.822" end="224.436" file="02JN112-2_Zendar_a11.wav"/>
    </S>
    <S id="a12">
        <FORM kindOf="original">a palalaut, a ru'alju'aljup a cawcau, amin a 'edril, a aljis, katua te'ung nua sacemel a adju'en nu namasan nimadju, kedri a sikipu'arutan tua kanen.</FORM>
        <PHON kindOf="original">a pa…≠a…≠aut, a ru Ēa éu Ēa éup a  ¶aw ¶au, amin a  Ē…ô…Ėi…≠, a a éis, katua t…ô ĒuŇč nua sa ¶…ôm…ô…≠ a a…Ču Ē…ôn nu namasan nima…Ču, k…ô…Ėi a sikipu Ēarutan tua kan…ôn.</PHON>
        <FORM kindOf="standard">a palalaut, a ru'alju'aljup a cawcau, amin a 'edril, a aljis, katua te'ung nua sacemel a adju'en nu namasan nimadju, kedri a sikipu'arutan tua kanen.</FORM>
        <PHON kindOf="standard">a pa…≠a…≠aut, a ru Ēa éu Ēa éup a  ¶aw ¶au, amin a  Ē…ô…Ėi…≠, a a éis, katua t…ô ĒuŇč nua sa ¶…ôm…ô…≠ a a…Ču Ē…ôn nu namasan nima…Ču, k…ô…Ėi a sikipu Ēarutan tua kan…ôn.</PHON>
        <AUDIO start="224.436" end="247.656" file="02JN112-2_Zendar_a12.wav"/>
    </S>
    <S id="a13">
        <FORM kindOf="original">ljakua a puzangalan nua varung niamadju napaka napakatjezua aravac, ayatua a namasan tjaljakudralan tua kakavelian tjaymadju, mavan a neka nu namaulj i 'inaljan tua siljeva nimadju.</FORM>
        <PHON kindOf="original"> éakua a puzaŇča…≠an nua varuŇč niama…Ču napaka napaka ¶…ôzua arava ¶, ajatua a namasan  ¶a éaku…Ėa…≠an tua kakav…ô…≠ian  ¶ajma…Ču, mavan a n…ôka nu namau é i  Ēina éan tua si é…ôva nima…Ču.</PHON>
        <FORM kindOf="standard">ljakua a puzangalan nua varung niamadju napaka napakatjezua aravac, ayatua a namasan tjaljakudralan tua kakavelian tjaymadju, mavan a neka nu namaulj i 'inaljan tua siljeva nimadju.</FORM>
        <PHON kindOf="standard"> éakua a puzaŇča…≠an nua varuŇč niama…Ču napaka napaka ¶…ôzua arava ¶, ajatua a namasan  ¶a éaku…Ėa…≠an tua kakav…ô…≠ian  ¶ajma…Ču, mavan a n…ôka nu namau é i  Ēina éan tua si é…ôva nima…Ču.</PHON>
        <AUDIO start="247.656" end="277.200" file="02JN112-2_Zendar_a13.wav"/>
    </S>
    <S id="a14">
        <FORM kindOf="original">azua ini ka kemeljang tu semiljeva tua puzangalan a cawcau, pazangal aravac a mi malingdjelj i tua kinateveteveljan nua sepaiwan zuku.</FORM>
        <PHON kindOf="original">azua ini ka k…ôm…ô éaŇč tu s…ômi é…ôva tua puzaŇča…≠an a  ¶aw ¶au, pazaŇča…≠ arava ¶ a mi ma…≠iŇč…Č…ô é i tua kinat…ôv…ôt…ôv…ô éan nua s…ôpaiwan zuku.</PHON>
        <FORM kindOf="standard">azua ini ka kemeljang tu semiljeva tua puzangalan a cawcau, pazangal aravac a mi malingdjelj i tua kinateveteveljan nua sepaiwan zuku.</FORM>
        <PHON kindOf="standard">azua ini ka k…ôm…ô éaŇč tu s…ômi é…ôva tua puzaŇča…≠an a  ¶aw ¶au, pazaŇča…≠ arava ¶ a mi ma…≠iŇč…Č…ô é i tua kinat…ôv…ôt…ôv…ô éan nua s…ôpaiwan zuku.</PHON>
        <AUDIO start="277.200" end="295.490" file="02JN112-2_Zendar_a14.wav"/>
    </S>
    <S id="a15">
        <FORM kindOf="original">&quot;inikatjen a venudilj tua tjakinamangua', azua na naseman tjaparavac tua sala salasaladj mavan a nasancawcau.&quot; aicu a tulu, ini ka ini ka kaulavan angata a sepaiwan zuku a cawcau.</FORM>
        <PHON kindOf="original">&quot;inika ¶…ôn a v…ônudi é tua  ¶akinamaŇčua Ē, azua na nas…ôman  ¶aparava ¶ tua sa…≠a sa…≠asa…≠a…Č mavan a nasan ¶aw ¶au.&quot; ai ¶u a tu…≠u, ini ka ini ka kau…≠avan aŇčata a s…ôpaiwan zuku a  ¶aw ¶au.</PHON>
        <FORM kindOf="standard">&quot;inikatjen a venudilj tua tjakinamangua', azua na naseman tjaparavac tua sala salasaladj mavan a nasancawcau.&quot; aicu a tulu, ini ka ini ka kaulavan angata a sepaiwan zuku a cawcau.</FORM>
        <PHON kindOf="standard">&quot;inika ¶…ôn a v…ônudi é tua  ¶akinamaŇčua Ē, azua na nas…ôman  ¶aparava ¶ tua sa…≠a sa…≠asa…≠a…Č mavan a nasan ¶aw ¶au.&quot; ai ¶u a tu…≠u, ini ka ini ka kau…≠avan aŇčata a s…ôpaiwan zuku a  ¶aw ¶au.</PHON>
        <AUDIO start="295.490" end="322.197" file="02JN112-2_Zendar_a15.wav"/>
    </S>
</TEXT>